{
    "foodsMenu": [
        {
            "title": "Entrada",
            "rows": [
                {
                    "name": "Frozen yoghurt",
                    "price": 1523.01,
                    "description": "hola mundo cuantos also tenfo en estas cosas, hace mucho ya",
                    "img": "vite.svg"
                },
                {
                    "name": "Sushi",
                    "price": 1523.01,
                    "description": "hola mundo cuantos also tenfo en estas cosas, hace mucho ya",
                    "img": "vite.svg"
                },
                {
                    "name": "Hola mundo",
                    "price": 1523.01,
                    "description": "hola mundo cuantos also tenfo en estas cosas, hace mucho ya",
                    "img": "vite.svg"
                },
                {
                    "name": "Ice cream sandwich",
                    "price": 23.01,
                    "description": "hola mundo cuantos also tenfo en estas cosas, hace mucho ya",
                    "img": "vite.svg"
                }
            ]
        },
        {
            "title": "Juntes",
            "rows": [
                {
                    "name": "Frozen yoghurt",
                    "price": 1523.01,
                    "description": "hola mundo cuantos also tenfo en estas cosas, hace mucho ya",
                    "img": "vite.svg"
                },
                {
                    "name": "Sushi",
                    "price": 1523.01,
                    "description": "hola mundo cuantos also tenfo en estas cosas, hace mucho ya",
                    "img": "vite.svg"
                },
                {
                    "name": "Hola mundo",
                    "price": 1523.01,
                    "description": "hola mundo cuantos also tenfo en estas cosas, hace mucho ya",
                    "img": "vite.svg"
                },
                {
                    "name": "Ice cream sandwich",
                    "price": 23.01,
                    "description": "hola mundo cuantos also tenfo en estas cosas, hace mucho ya",
                    "img": "vite.svg"
                }
            ]
        },
        {
            "title": "Platos",
            "rows": [
                {
                    "name": "Frozen yoghurt",
                    "price": 1523.01,
                    "description": "hola mundo cuantos also tenfo en estas cosas, hace mucho ya",
                    "img": "vite.svg"
                },
                {
                    "name": "Ice cream sandwich",
                    "price": 23.01,
                    "description": "hola mundo cuantos also tenfo en estas cosas, hace mucho ya",
                    "img": "vite.svg"
                }
            ]
        },
        {
            "title": "Sushinis",
            "rows": [
                {
                    "name": "Frozen yoghurt",
                    "price": 1523.01,
                    "description": "hola mundo cuantos also tenfo en estas cosas, hace mucho ya",
                    "img": "vite.svg"
                },
                {
                    "name": "Ice cream sandwich",
                    "price": 23.01,
                    "description": "hola mundo cuantos also tenfo en estas cosas, hace mucho ya",
                    "img": "vite.svg"
                }
            ]
        }
    ]
}
